kmon/__init__.py
kmon/utility.py
kmon/factories/__init__.py
kmon/factories/storage_factory.py
kmon/model/__init__.py
kmon/model/credential.py
kmon/notification/__init__.py
kmon/notification/notification_client.py
kmon/notification/slack.py
kmon/notification/sns.py
kmon/storage/__init__.py
kmon/storage/oss_client.py
kmon/storage/s3_client.py
kmon/storage/storage_client.py
kmon/stream/__init__.py
kmon/stream/kmsf_stream.py
tests/TEST_FUNC.py
tests/__init__.py
tests/test_streamer.py
tests/test_utility.py
kmon_file_streamer-0.1.5.dist-info/LICENSE
kmon_file_streamer-0.1.5.dist-info/METADATA
kmon_file_streamer-0.1.5.dist-info/WHEEL
kmon_file_streamer-0.1.5.dist-info/top_level.txt
kmon_file_streamer-0.1.5.dist-info/RECORD
